{
  "theme": "moonstone",
  "lightStyle": "minimal-light",
  "darkStyle": "minimal-dark",
  "lightScheme": "minimal-default-light",
  "darkScheme": "minimal-default-dark",
  "editorFont": "Herz",
  "lineHeight": 1.8,
  "lineWidth": 60,
  "lineWidthWide": 70,
  "maxWidth": 90,
  "textNormal": 17,
  "textSmall": 15,
  "imgGrid": true,
  "imgWidth": "img-default-width",
  "tableWidth": "table-default-width",
  "iframeWidth": "iframe-default-width",
  "mapWidth": "map-default-width",
  "chartWidth": "chart-default-width",
  "colorfulHeadings": true,
  "colorfulFrame": false,
  "colorfulActiveStates": true,
  "trimNames": true,
  "labeledNav": true,
  "fullWidthMedia": true,
  "bordersToggle": false,
  "minimalStatus": true,
  "focusMode": false,
  "underlineInternal": true,
  "underlineExternal": true,
  "useSystemTheme": false,
  "folding": true,
  "lineNumbers": false,
  "readableLineLength": true,
  "devBlockWidth": false
}